itk/CudaCommonPython.py
itk/_CudaCommonPython.pyd
itk/__init_cudacommon__.py
itk/itkCudaDataManagerPython.py
itk/itkCudaImageDataManagerPython.py
itk/itkCudaImagePython.py
itk/itkImageSourceCudaCommonPython.py
itk/itkImageToImageFilterCudaCommonPython.py
itk/Configuration/CudaCommonConfig.py
itk/Configuration/CudaCommon_snake_case.py
itk_cudacommon.libs/.load-order-itk_cudacommon-1.1.0
itk_cudacommon.libs/msvcp140.dll
itk_cudacommon.libs/vcruntime140_1.dll
itk_cudacommon-1.1.0.dist-info/DELVEWHEEL
itk_cudacommon-1.1.0.dist-info/LICENSE
itk_cudacommon-1.1.0.dist-info/METADATA
itk_cudacommon-1.1.0.dist-info/WHEEL
itk_cudacommon-1.1.0.dist-info/top_level.txt
itk_cudacommon-1.1.0.dist-info/RECORD
