Metadata-Version: 2.1
Name: itk-cudacommon
Version: 1.1.0
Summary: Framework for processing images with Cuda.
Home-page: https://github.com/RTKConsortium/ITKCudaCommon
Download-URL: https://github.com/RTKConsortium/ITKCudaCommon
Author: RTK Consortium
Author-email: simon.rit@creatis.insa-lyon.fr
License: Apache
Classifier: License :: OSI Approved :: Apache Software License
Classifier: Programming Language :: Python
Classifier: Programming Language :: C++
Classifier: Development Status :: 4 - Beta
Classifier: Intended Audience :: Developers
Classifier: Intended Audience :: Education
Classifier: Intended Audience :: Healthcare Industry
Classifier: Intended Audience :: Science/Research
Classifier: Topic :: Scientific/Engineering
Classifier: Topic :: Scientific/Engineering :: Medical Science Apps.
Classifier: Topic :: Scientific/Engineering :: Information Analysis
Classifier: Topic :: Software Development :: Libraries
Classifier: Operating System :: Android
Classifier: Operating System :: Microsoft :: Windows
Classifier: Operating System :: POSIX
Classifier: Operating System :: Unix
Classifier: Operating System :: MacOS
License-File: LICENSE
Requires-Dist: itk ==5.4.*
